CA_Final_Project/CA_Final_Project.srcs/sources_1/new/Immgen.v
`timescale 1ns / 1ps
// Lab 11 - Task 1
// Immediate Generator: supports I, S, and B-type RISC-V immediate formats
module immGen(
    input  [31:0] instruction,
    output reg [63:0] imm_data
);
    wire [1:0] code = instruction[6:5];

    always @(*) begin
        case (code)
            // I-type (opcode bits [6:5] = 00): loads, ADDI, etc.
            2'b00 : imm_data = {{52{instruction[31]}}, instruction[31:20]};

            // S-type (opcode bits [6:5] = 01): stores
            2'b01 : imm_data = {{52{instruction[31]}}, instruction[31:25], instruction[11:7]};

            // B-type (opcode bits [6:5] = 11): branches
            2'b11 : imm_data = {{52{instruction[31]}}, instruction[31], instruction[7],
                                  instruction[30:25], instruction[11:8]};

            default: imm_data = 64'b0;
        endcase
    end
endmodule

CA_Final_Project/CA_Final_Project.srcs/sources_1/new/Mux2.v
`timescale 1ns / 1ps
// Lab 11 - Task 1
// 2-to-1 Mux: selects next PC value
//   PCSrc = 0 -> PC + 4 (sequential)
//   PCSrc = 1 -> Branch target
module mux2(
    input  [63:0] In0,      // PC + 4
    input  [63:0] In1,      // Branch target
    input         PCSrc,
    output [63:0] Out
);
    assign Out = PCSrc ? In1 : In0;
endmodule

CA_Final_Project/CA_Final_Project.srcs/sources_1/new/Branchadder.v
`timescale 1ns / 1ps
// Lab 11 - Task 1
// Branch Adder: computes PC + (sign-extended immediate << 1)
// Per RISC-V spec, B-type immediates encode multiples of 2;
// the immGen already gives the raw imm field, so we shift left by 1 here.
module branchAdder(
    input  [63:0] PC,
    input  [63:0] Imm,          // sign-extended immediate from immGen
    output [63:0] BranchTarget
);
    assign BranchTarget = PC + (Imm << 1);
endmodule

CA_Final_Project/CA_Final_Project.srcs/sources_1/new/Pcadder.v
`timescale 1ns / 1ps
// Lab 11 - Task 1
// PC Adder: computes PC + 4 (next sequential instruction address)
module pcAdder(
    input  [63:0] PC,
    output [63:0] PC_Plus4
);
    assign PC_Plus4 = PC + 64'd4;
endmodule

CA_Final_Project/CA_Final_Project.srcs/sources_1/new/Programcounter.v
`timescale 1ns / 1ps
// Lab 11 - Task 1
// Program Counter: stores and updates PC on every positive clock edge
module ProgramCounter(
    input        clk,
    input        reset,
    input  [63:0] PC_In,
    output reg [63:0] PC_Out
);
    always @(posedge clk) begin
        if (reset)
            PC_Out <= 64'b0;
        else
            PC_Out <= PC_In;
    end
endmodule

CA_Final_Project/CA_Final_Project.srcs/sim_1/new/tb_Task1.v
`timescale 1ns / 1ps
// Lab 11 - Task 1 Testbench
// Verifies: PC+4 sequential update, branch target update, immediate generation
module tb_Task1;

    // ---------- Clock & Reset ----------
    reg clk, reset;
    initial clk = 0;
    always #5 clk = ~clk;   // 10 ns period

    // ---------- Wires ----------
    wire [63:0] PC_Out;       // from ProgramCounter
    wire [63:0] PC_Plus4;     // from pcAdder
    wire [63:0] BranchTarget; // from branchAdder
    wire [63:0] PC_Next;      // from mux2
    wire [63:0] ImmOut;       // from immGen

    // ---------- PCSrc control (manually toggled in test) ----------
    reg PCSrc;

    // ---------- Immediate generation test instruction ----------
    // I-type:  ADDI x5, x0, 16   -> imm = 16
    //   imm[11:0] = 12'h010, rs1=x0, funct3=000, rd=x5, opcode=0010011
    reg [31:0] test_instr;

    // ---------- DUT instantiations ----------
    ProgramCounter PC_inst (
        .clk    (clk),
        .reset  (reset),
        .PC_In  (PC_Next),
        .PC_Out (PC_Out)
    );

    pcAdder PCA (
        .PC       (PC_Out),
        .PC_Plus4 (PC_Plus4)
    );

    // Use a fixed signed immediate for branch test: imm = 8
    // branchTarget = PC + (8 << 1) = PC + 16
    branchAdder BRA (
        .PC           (PC_Out),
        .Imm          (64'd8),      // test immediate
        .BranchTarget (BranchTarget)
    );

    mux2 MUX (
        .In0    (PC_Plus4),
        .In1    (BranchTarget),
        .PCSrc  (PCSrc),
        .Out    (PC_Next)
    );

    immGen IG (
        .instruction (test_instr),
        .imm_data    (ImmOut)
    );

    // ---------- Stimulus ----------
    integer i;
    initial begin
        $dumpfile("tb_Task1.vcd");
        $dumpvars(0, tb_Task1);

        // ---- Reset ----
        reset = 1; PCSrc = 0;
        test_instr = 32'h01000293; // ADDI x5, x0, 16  (imm=16)
        @(posedge clk); #1;
        reset = 0;

        // ---- Test: PC increments by 4 (PCSrc=0) ----
        $display("\n--- Sequential PC (PCSrc=0) ---");
        for (i = 0; i < 5; i = i + 1) begin
            @(posedge clk); #1;
            $display("  PC_Out=%0d  PC_Plus4=%0d", PC_Out, PC_Plus4);
        end

        // ---- Test: branch taken (PCSrc=1) ----
        $display("\n--- Branch taken (PCSrc=1) ---");
        PCSrc = 1;
        @(posedge clk); #1;
        $display("  PC_Out=%0d  BranchTarget=%0d  PC_Next=%0d",
                  PC_Out, BranchTarget, PC_Next);
        @(posedge clk); #1;
        $display("  PC_Out=%0d (should be previous BranchTarget)", PC_Out);

        // ---- Return to sequential ----
        PCSrc = 0;
        @(posedge clk); #1;
        $display("  PC_Out=%0d  PC_Plus4=%0d  (sequential again)", PC_Out, PC_Plus4);

        // ---- Test: Immediate generation ----
        $display("\n--- Immediate Generation ---");

        // I-type: imm = 16
        test_instr = 32'h01000293; // ADDI x5, x0, 16
        #1; $display("  I-type  instr=0x%08h  imm_data=%0d  (expected 16)",   test_instr, ImmOut);

        // S-type: imm = 4  (SW rs2, 4(rs1))
        // imm[11:5]=0000000, imm[4:0]=00100 -> instr[31:25]=7'b0, instr[11:7]=5'b00100
        test_instr = 32'h00202223; // SW x2, 4(x0)
        #1; $display("  S-type  instr=0x%08h  imm_data=%0d  (expected 4)",    test_instr, ImmOut);

        // B-type: imm = 8  (BEQ x0, x0, +16 bytes -> imm field =8)
        // BEQ x0,x0,8:  imm[12|10:5]=0000000, rs2=x0, rs1=x0, funct3=000, imm[4:1|11]=1000 0, opcode=1100011
        test_instr = 32'h00000463; // BEQ x0, x0, +8
        #1; $display("  B-type  instr=0x%08h  imm_data=%0d  (expected 4)",    test_instr, ImmOut);

        // Negative I-type: imm = -1
        test_instr = 32'hfff00293; // ADDI x5, x0, -1
        #1; $display("  I-type  instr=0x%08h  imm_data=%0d  (expected -1 / 0xFFF...FFFF)", test_instr, $signed(ImmOut));

        $display("\n--- All tests complete ---");
        #20 $finish;
    end

endmodule

CA_Final_Project/CA_Final_Project.sim/sim_1/behav/xsim/tb_Task1.vcd
$date
   Sun Apr 19 16:58:44 2026
$end
$version
  2020.1
$end
$timescale
  1ps
$end
$scope module tb_Task1 $end
$var reg 1 ! clk $end
$var reg 1 " reset $end
$var wire 64 # PC_Out [63:0] $end
$var wire 64 $ PC_Plus4 [63:0] $end
$var wire 64 % BranchTarget [63:0] $end
$var wire 64 & PC_Next [63:0] $end
$var wire 64 ' ImmOut [63:0] $end
$var reg 1 ( PCSrc $end
$var reg 32 ) test_instr [31:0] $end
$var integer 32 * i $end
$scope module PC_inst $end
$var wire 1 + clk $end
$var wire 1 , reset $end
$var wire 64 & PC_In [63:0] $end
$var reg 64 - PC_Out [63:0] $end
$upscope $end
$scope module PCA $end
$var wire 64 # PC [63:0] $end
$var wire 64 $ PC_Plus4 [63:0] $end
$upscope $end
$scope module BRA $end
$var wire 64 # PC [63:0] $end
$var wire 64 . Imm [63:0] $end
$var wire 64 % BranchTarget [63:0] $end
$upscope $end
$scope module MUX $end
$var wire 64 $ In0 [63:0] $end
$var wire 64 % In1 [63:0] $end
$var wire 1 / PCSrc $end
$var wire 64 & Out [63:0] $end
$upscope $end
$scope module IG $end
$var wire 32 0 instruction [31:0] $end
$var reg 64 1 imm_data [63:0] $end
$var wire 2 2 code [1:0] $end
$upscope $end
$upscope $end
$enddefinitions $end
#0
$dumpvars
0!
1"
bx #
bx $
bx %
bx &
b10000 '
0(
b1000000000000001010010011 )
bx *
0+
1,
bx -
b1000 .
0/
b1000000000000001010010011 0
b10000 1
b0 2
$end
#5000
1!
b0 #
b100 $
b10000 %
b100 &
1+
b0 -
#6000
0"
b0 *
0,
#10000
0!
0+
#15000
1!
b100 #
b1000 $
b10100 %
b1000 &
1+
b100 -
#16000
b1 *
#20000
0!
0+
#25000
1!
b1000 #
b1100 $
b11000 %
b1100 &
1+
b1000 -
#26000
b10 *
#30000
0!
0+
#35000
1!
b1100 #
b10000 $
b11100 %
b10000 &
1+
b1100 -
#36000
b11 *
#40000
0!
0+
#45000
1!
b10000 #
b10100 $
b100000 %
b10100 &
1+
b10000 -
#46000
b100 *
#50000
0!
0+
#55000
1!
b10100 #
b11000 $
b100100 %
b11000 &
1+
b10100 -
#56000
b100100 &
1(
b101 *
1/
#60000
0!
0+
#65000
1!
b100100 #
b101000 $
b110100 %
b110100 &
1+
b100100 -
#70000
0!
0+
#75000
1!
b110100 #
b111000 $
b1000100 %
b1000100 &
1+
b110100 -
#76000
b111000 &
0(
0/
#80000
0!
0+
#85000
1!
b111000 #
b111100 $
b1001000 %
b111100 &
1+
b111000 -
#86000
b1000000000000001010010011 )
#87000
b100 '
b1000000010001000100011 )
b1000000010001000100011 0
b100 1
b1 2
#88000
b10001100011 )
b10001100011 0
b100 1
b11 2
#89000
b1111111111111111111111111111111111111111111111111111111111111111 '
b11111111111100000000001010010011 )
b11111111111100000000001010010011 0
b1111111111111111111111111111111111111111111111111111111111111111 1
b0 2
#90000
0!
0+
#95000
1!
b111100 #
b1000000 $
b1001100 %
b1000000 &
1+
b111100 -
#100000
0!
0+
#105000
1!
b1000000 #
b1000100 $
b1010000 %
b1000100 &
1+
b1000000 -
